charLLM/NPLM.py
charLLM/__init__.py
charLLM-0.0.7.dist-info/LICENCE
charLLM-0.0.7.dist-info/METADATA
charLLM-0.0.7.dist-info/WHEEL
charLLM-0.0.7.dist-info/top_level.txt
charLLM-0.0.7.dist-info/RECORD
