Metadata-Version: 2.1
Name: charLLM
Version: 0.0.7
Summary: Character Level Language Models 🕺🏽
Home-page: https://github.com/RAravindDS/CharLLMs
Author: Aravind
Author-email: aravindan22052001@gmail.com
Project-URL: Bug Tracker, https://github.com/RAravindDS/CharLLMs/issues
Classifier: Programming Language :: Python :: 3
Classifier: License :: OSI Approved :: MIT License
Classifier: Operating System :: OS Independent
Requires-Python: >=3.8
License-File: LICENCE
